zmeyweb/__init__.py
zmeyweb/auth.py
zmeyweb/core.py
zmeyweb/db.py
zmeyweb/event.py
zmeyweb/events_process.py
zmeyweb/pipeline.py
zmeyweb/pipeline_task.py
zmeyweb/scheduler.py
zmeyweb/task.py
zmeyweb/task_template.py
zmeyweb/user.py
zmeyweb/worker.py
zmeyweb/zm_client.py
zmeyweb/zmserver.cng
zmeyweb/api/api.py
zmeyweb/api/api_event.py
zmeyweb/api/api_pipeline.py
zmeyweb/api/api_pipeline_task.py
zmeyweb/api/api_scheduler.py
zmeyweb/api/api_task.py
zmeyweb/api/api_task_template.py
zmeyweb/api/api_user.py
zmeyweb/api/api_worker.py
zmeyweb/html/base.html
zmeyweb/html/auth/login.html
zmeyweb/html/auth/register.html
zmeyweb/html/gui/admin.html
zmeyweb/html/gui/index.html
zmeyweb/static/favicon.ico
zmeyweb/static/css/bootstrap.min.css
zmeyweb/static/css/bootstrap.min.css.map
zmeyweb/static/css/style.css
zmeyweb/static/images/label.svg
zmeyweb/static/js/admin.js
zmeyweb/static/js/bundle.js
zmeyweb/static/js/fonts/fontello.woff!static
zmeyweb/static/js/fonts/fontello.woff2!static
zmeyweb-1.0.1.dist-info/LICENSE
zmeyweb-1.0.1.dist-info/METADATA
zmeyweb-1.0.1.dist-info/WHEEL
zmeyweb-1.0.1.dist-info/top_level.txt
zmeyweb-1.0.1.dist-info/RECORD
