Metadata-Version: 2.1
Name: zmeyweb
Version: 1.0.1
Summary: Application for schedule and monitor workflows
Home-page: https://github.com/Tyill/zmey
License: MIT
Platform: UNKNOWN
Classifier: License :: OSI Approved :: MIT License
Classifier: Operating System :: OS Independent
Classifier: Intended Audience :: Developers
Classifier: Environment :: Web Environment
Classifier: Programming Language :: Python :: 3.6
Classifier: Topic :: System :: Monitoring
License-File: LICENSE
Requires-Dist: flask
